mongox/__init__.py
mongox/_helpers.py
mongox/database.py
mongox/exceptions.py
mongox/expressions.py
mongox/fields.py
mongox/index.py
mongox/models.py
mongox-0.1.2.dist-info/LICENSE
mongox-0.1.2.dist-info/WHEEL
mongox-0.1.2.dist-info/METADATA
mongox-0.1.2.dist-info/RECORD
